README.rst
cpchunk.py
setup.py
cpchunk.egg-info/PKG-INFO
cpchunk.egg-info/SOURCES.txt
cpchunk.egg-info/dependency_links.txt
cpchunk.egg-info/entry_points.txt
cpchunk.egg-info/top_level.txt