Metadata-Version: 1.1
Name: cpchunk
Version: 1.0.0.4
Summary: A tool for copying chunks of files
Home-page: http://github.com/furrykef/cpchunk
Author: Kef Schecter
Author-email: furrykef@gmail.com
License: MIT
Platform: UNKNOWN
Classifier: Development Status :: 5 - Production/Stable
Classifier: License :: OSI Approved :: MIT License
Classifier: Programming Language :: Python :: 3.4
Classifier: Topic :: Utilities
